rustyssim/__init__.py
rustyssim/__init__.pyi
rustyssim/py.typed
rustyssim/rustyssim.abi3.so
rustyssim-0.5.1.dist-info/METADATA
rustyssim-0.5.1.dist-info/WHEEL
rustyssim-0.5.1.dist-info/RECORD
