Metadata-Version: 2.4
Name: rustyssim
Version: 0.5.1
Classifier: Development Status :: 5 - Production/Stable
Classifier: License :: OSI Approved :: MIT License
Classifier: Operating System :: OS Independent
Classifier: Programming Language :: Python
Classifier: Programming Language :: Python :: 3
Classifier: Programming Language :: Python :: 3 :: Only
Classifier: Programming Language :: Python :: 3.9
Classifier: Programming Language :: Python :: 3.10
Classifier: Programming Language :: Python :: 3.11
Classifier: Programming Language :: Python :: 3.12
Classifier: Programming Language :: Python :: 3.13
Classifier: Programming Language :: Rust
Classifier: Typing :: Typed
Requires-Dist: polars>=1.36.1
Summary: This package provides a Python interface to parse SSIM files into a Polars DataFrame.
Keywords: parsing,ssim,data
Author-email: William Green <wcagreen24@gmail.com>
License-Expression: MIT
Requires-Python: >=3.9
Project-URL: Documentation, https://github.com/wcagreen/rusty-ssim/blob/main/docs/python.md
Project-URL: Repository, https://github.com/wcagreen/rusty-ssim
